MANIFEST.in
README.md
pyproject.toml
setup.cfg
setup.py
Apywy.egg-info/PKG-INFO
Apywy.egg-info/SOURCES.txt
Apywy.egg-info/dependency_links.txt
Apywy.egg-info/top_level.txt
apywy/__init__.py
apywy/decorators.py
apywy/fields.py
apywy/schema.py
apywy/schema_tool.py
apywy/static_funcs.py
apywy/adapters/__init__.py
apywy/adapters/initializers.py
apywy/adapters/repositories.py
apywy/api/__init__.py
apywy/api/apps.py
apywy/api/urls.py
apywy/api/views.py
apywy/constants/__init__.py
apywy/constants/const.py
apywy/constants/exceptions.py
apywy/constants/request/__init__.py
apywy/constants/request/const.py
apywy/constants/response/__init__.py
apywy/constants/response/const.py
apywy/domain/__init__.py
apywy/domain/entities.py
apywy/serializers/__init__.py
apywy/serializers/serializers.py
apywy/static/index.css
apywy/static/index.js
apywy/templates/apywy/index.html
apywy/utilities/__init__.py
apywy/utilities/custom_typing.py