Metadata-Version: 2.1
Name: Apywy
Version: 0.0.5
Summary: swagger analog
Home-page: https://github.com/Rwwwrl/ApyWy
Author: Alexey Sosov
Author-email: lesh.solowiew@yandex.ru
License: BSD-3-Clause
Platform: UNKNOWN
Classifier: Environment :: Web Environment
Classifier: Framework :: Django
Classifier: Framework :: Django :: 3.0
Classifier: Framework :: Django :: 4.0
Classifier: Intended Audience :: Developers
Classifier: License :: OSI Approved :: BSD License
Classifier: Operating System :: OS Independent
Classifier: Programming Language :: Python
Classifier: Programming Language :: Python :: 3.7
Requires-Python: >=3.7
